setup.py
bin/xrpi
xrpi/__init__.py
xrpi/xrpi.py
xrpi_test_12.10.16.egg-info/PKG-INFO
xrpi_test_12.10.16.egg-info/SOURCES.txt
xrpi_test_12.10.16.egg-info/dependency_links.txt
xrpi_test_12.10.16.egg-info/requires.txt
xrpi_test_12.10.16.egg-info/top_level.txt
xrpi_test_12.10.16.egg-info/zip-safe