Metadata-Version: 1.0
Name: xrpi-test-12.10.16
Version: 0.0.2
Summary: XGBoost powered RNA-Protein Interaction prediction
Home-page: UNKNOWN
Author: Sanket Gupte
Author-email: sanketgupte14@gmail.com
License: Not Free Stuff
Platform: UNKNOWN
